classify/__init__.py
classify/xbinary_classifier.py
xbinary_classifier-0.6.0.dist-info/LICENSE
xbinary_classifier-0.6.0.dist-info/METADATA
xbinary_classifier-0.6.0.dist-info/WHEEL
xbinary_classifier-0.6.0.dist-info/top_level.txt
xbinary_classifier-0.6.0.dist-info/RECORD
