Metadata-Version: 2.1
Name: xbinary_classifier
Version: 0.6.0
License-File: LICENSE
Requires-Dist: numpy
Requires-Dist: seaborn
Requires-Dist: scikit-learn
Requires-Dist: matplotlib
Requires-Dist: joblib
Requires-Dist: pandas
Requires-Dist: astropy
